{
    "namespace": "Project.Helixbase",
    "references": [
        "Foundation.*",
        "Feature.*",
        "Project.Common"
    ],
    "items": {
        "includes": [
            {
                "name": "Templates",
                "path": "/sitecore/templates/Project/Helixbase",
                "database": "master"
            },
            {
                "name": "Renderings",
                "path": "/sitecore/layout/renderings/Project/Helixbase",
                "database": "master"
            },
            {
                "name": "Layouts",
                "path": "/sitecore/layout/layouts/Project/Helixbase",
                "database": "master"
            },
            {
                "name": "PlaceholderSettings",
                "path": "/sitecore/layout/placeholder settings/Project/Helixbase",
                "database": "master"
            },
            {
                "name": "Models",
                "path": "/sitecore/layout/models/Project/Helixbase",
                "database": "master"
            },
            {
                "name": "Content",
                "path": "/sitecore/content/Helixbase",
                "database": "master"
            },
            {
                "name": "Media",
                "path": "/sitecore/media library/Project/Helixbase",
                "database": "master"
            },
            {
                "name": "Profiling",
                "path": "/sitecore/system/Marketing Control Panel/Profiles/Helixbase",
                "database": "master"
            },
            {
                "name": "Outcomes",
                "path": "/sitecore/system/Marketing Control Panel/Outcomes/Helixbase",
                "database": "master"
            },
            {
                "name": "Campaigns",
                "path": "/sitecore/system/Marketing Control Panel/Campaigns/Helixbase",
                "database": "master"
            }
        ]
    }
}